investments/__init__.py
investments/calculators.py
investments/cash.py
investments/currency.py
investments/deposit.py
investments/dividend.py
investments/fees.py
investments/interests.py
investments/money.py
investments/ticker.py
investments/trade.py
investments/trades_fifo.py
investments/withdraw.py
investments/data_providers/__init__.py
investments/data_providers/cache.py
investments/data_providers/cbr.py
investments/data_providers/moex.py
investments/ibdds/__init__.py
investments/ibdds/__main__.py
investments/ibdds/ibdds.py
investments/ibtax/__init__.py
investments/ibtax/__main__.py
investments/ibtax/ibtax.py
investments/ibtax/report_presenter.py
investments/report_parsers/__init__.py
investments/report_parsers/ib.py
investments/report_parsers/open_fr.py
investments-0.3.0.dist-info/METADATA
investments-0.3.0.dist-info/WHEEL
investments-0.3.0.dist-info/entry_points.txt
investments-0.3.0.dist-info/licenses/LICENSE.txt
investments-0.3.0.dist-info/RECORD
