Metadata-Version: 2.4
Name: investments
Version: 0.3.0
Summary: Analysis of Interactive Brokers reports for tax reporting in Russia
Project-URL: Repository, https://github.com/cdump/investments
Author-email: Maxim Andreev <andreevmaxim@gmail.com>
License-Expression: MIT
License-File: LICENSE.txt
Classifier: Development Status :: 3 - Alpha
Classifier: Environment :: Console
Classifier: License :: OSI Approved :: MIT License
Classifier: Programming Language :: Python :: 3 :: Only
Classifier: Topic :: Office/Business :: Financial :: Accounting
Classifier: Topic :: Office/Business :: Financial :: Investment
Requires-Python: >=3.12
Requires-Dist: aiomoex>=2.1
Requires-Dist: jinja2>=3.1
Requires-Dist: pandas>=2.2
Requires-Dist: requests>=2.31
Requires-Dist: tabulate>=0.9
Requires-Dist: weasyprint>=60.2
